stepper/__init__.py
stepper/commands/__init__.py
stepper/commands/commands.py
stepper/commands/get.py
stepper/commands/home.py
stepper/commands/move.py
stepper/commands/set.py
stepper/commands/system.py
stepper/device/__init__.py
stepper/device/device.py
stepper/serial_utilities/__init__.py
stepper/serial_utilities/serial_utilities.py
stepper/stepper_core/__init__.py
stepper/stepper_core/configs.py
stepper/stepper_core/exceptions.py
stepper/stepper_core/parameters.py
zdt_stepper-0.1.1.dist-info/LICENSE
zdt_stepper-0.1.1.dist-info/METADATA
zdt_stepper-0.1.1.dist-info/WHEEL
zdt_stepper-0.1.1.dist-info/top_level.txt
zdt_stepper-0.1.1.dist-info/RECORD
