Metadata-Version: 2.1
Name: zdt_stepper
Version: 0.1.1
Summary: ZDT stepper motor control library
Author-email: Yehe Liu <yehe@opsiclear.com>
License: MIT License
Keywords: stepper,motor,control
Classifier: Development Status :: 3 - Alpha
Classifier: Intended Audience :: Developers
Classifier: License :: OSI Approved :: MIT License
Classifier: Programming Language :: Python :: 3.10
Requires-Python: >=3.10
License-File: LICENSE
Requires-Dist: pyserial
Requires-Dist: pyyaml
Requires-Dist: tqdm
Provides-Extra: dev
Requires-Dist: ruff; extra == "dev"
Requires-Dist: pre-commit; extra == "dev"
Requires-Dist: twine; extra == "dev"
Provides-Extra: build
Requires-Dist: setuptools; extra == "build"
Requires-Dist: wheel; extra == "build"
Requires-Dist: build; extra == "build"
